tstgispypkg/__init__.py
tstgispypkg/common.py
tstgispypkg/tstgispypkg.py
tstgispypkg-0.0.1.dist-info/licenses/LICENSE
tstgispypkg-0.0.1.dist-info/METADATA
tstgispypkg-0.0.1.dist-info/WHEEL
tstgispypkg-0.0.1.dist-info/entry_points.txt
tstgispypkg-0.0.1.dist-info/top_level.txt
tstgispypkg-0.0.1.dist-info/RECORD
