Metadata-Version: 2.4
Name: tstgispypkg
Version: 0.0.1
Summary: A python package for geospatial analysis and mapping.
Author-email: Jingze Liu <jingze899@gmail.com>
License: MIT License
Project-URL: Homepage, https://github.com/BOOMovo/tstgispypkg
Keywords: tstgispypkg
Classifier: Intended Audience :: Developers
Classifier: License :: OSI Approved :: MIT License
Classifier: Natural Language :: English
Classifier: Programming Language :: Python :: 3.8
Classifier: Programming Language :: Python :: 3.9
Classifier: Programming Language :: Python :: 3.10
Classifier: Programming Language :: Python :: 3.11
Classifier: Programming Language :: Python :: 3.12
Requires-Python: >=3.8
License-File: LICENSE
Requires-Dist: numpy
Provides-Extra: all
Requires-Dist: tstgispypkg[extra]; extra == "all"
Provides-Extra: extra
Requires-Dist: pandas; extra == "extra"
Dynamic: license-file
